odoo/addons/web_pwa/README.rst
odoo/addons/web_pwa/__init__.py
odoo/addons/web_pwa/__manifest__.py
odoo/addons/web_pwa/controllers/__init__.py
odoo/addons/web_pwa/controllers/main.py
odoo/addons/web_pwa/i18n/da.po
odoo/addons/web_pwa/i18n/web_pwa.pot
odoo/addons/web_pwa/readme/CONFIGURE.rst
odoo/addons/web_pwa/readme/CONTRIBUTORS.rst
odoo/addons/web_pwa/readme/DESCRIPTION.rst
odoo/addons/web_pwa/readme/INSTALL.rst
odoo/addons/web_pwa/readme/ROADMAP.rst
odoo/addons/web_pwa/static/description/icon.png
odoo/addons/web_pwa/static/description/index.html
odoo/addons/web_pwa/static/description/pwa.png
odoo/addons/web_pwa/static/img/icons/icon-128x128.png
odoo/addons/web_pwa/static/img/icons/icon-144x144.png
odoo/addons/web_pwa/static/img/icons/icon-152x152.png
odoo/addons/web_pwa/static/img/icons/icon-192x192.png
odoo/addons/web_pwa/static/img/icons/icon-256x256.png
odoo/addons/web_pwa/static/img/icons/icon-512x512.png
odoo/addons/web_pwa/static/src/js/pwa_install.js
odoo/addons/web_pwa/static/src/xml/pwa_install.xml
odoo/addons/web_pwa/views/webclient_templates.xml
odoo12_addon_web_pwa-12.0.1.0.0.99.dev4.dist-info/METADATA
odoo12_addon_web_pwa-12.0.1.0.0.99.dev4.dist-info/WHEEL
odoo12_addon_web_pwa-12.0.1.0.0.99.dev4.dist-info/top_level.txt
odoo12_addon_web_pwa-12.0.1.0.0.99.dev4.dist-info/RECORD
